keecli/cli.py
keecli/database.py
keecli-0.2.2.dist-info/LICENSE
keecli-0.2.2.dist-info/METADATA
keecli-0.2.2.dist-info/WHEEL
keecli-0.2.2.dist-info/entry_points.txt
keecli-0.2.2.dist-info/RECORD
