Metadata-Version: 2.1
Name: keecli
Version: 0.2.2
Summary: KeeCLI is a cli to the password manager KeePass
License: GPL-3.0-or-later
Author: Leo Perard
Author-email: leo.perard@gmail.com
Requires-Python: >=3.10,<4.0
Classifier: License :: OSI Approved :: GNU General Public License v3 or later (GPLv3+)
Classifier: Programming Language :: Python :: 3
Classifier: Programming Language :: Python :: 3.10
Classifier: Programming Language :: Python :: 3.11
Requires-Dist: click (>=8.1.6,<9.0.0)
Requires-Dist: pykeepass (>=4.0.5,<5.0.0)
Requires-Dist: pyperclip (>=1.8.2,<2.0.0)
Requires-Dist: structlog (>=23.1.0,<24.0.0)
